MANIFEST.in
README.rst
setup.py
cpuutilization/__init__.py
cpuutilization/cpuutilization.py
py_cpuutilization.egg-info/PKG-INFO
py_cpuutilization.egg-info/SOURCES.txt
py_cpuutilization.egg-info/dependency_links.txt
py_cpuutilization.egg-info/top_level.txt