Metadata-Version: 1.1
Name: py-cpuutilization
Version: 0.1.0
Summary: A module for getting the CPU utilization on any OS with Python 2 & 3
Home-page: https://github.com/workhorsy/py-cpuutilization
Author: Matthew Brennan Jones
Author-email: matthew.brennan.jones@gmail.com
License: MIT
Platform: UNKNOWN
Classifier: Development Status :: 4 - Beta
Classifier: Topic :: Utilities
Classifier: License :: OSI Approved :: MIT License
